waterfall_logging/__init__.py
waterfall_logging/context_manager.py
waterfall_logging/decorator.py
waterfall_logging/log.py
waterfall_logging/utils.py
waterfall_logging-0.1.0.dist-info/LICENSE
waterfall_logging-0.1.0.dist-info/WHEEL
waterfall_logging-0.1.0.dist-info/METADATA
waterfall_logging-0.1.0.dist-info/RECORD
