Metadata-Version: 2.1
Name: waterfall-logging
Version: 0.1.0
Summary: Waterfall statistic logging for data quality or filtering steps.
Home-page: https://github.com/LouisdeBruijn/waterfall-logging
License: gnu-3.0
Keywords: waterfall,DQ,logging
Author: Louis de Bruijn
Maintainer: Louis de Bruijn
Requires-Python: >=3.8.1,<4.0
Classifier: License :: Other/Proprietary License
Classifier: Programming Language :: Python :: 3
Classifier: Programming Language :: Python :: 3.9
Classifier: Programming Language :: Python :: 3.10
Classifier: Programming Language :: Python :: 3.11
Requires-Dist: kaleido (==0.2.1)
Requires-Dist: pandas (>=1.5.3,<2.0.0)
Requires-Dist: plotly (>=5.13.0,<6.0.0)
Requires-Dist: pyspark (>=3.3.1,<4.0.0)
Requires-Dist: tabulate (>=0.9.0,<0.10.0)
Project-URL: Documentation, https://LouisdeBruijn.github.io/waterfall-logging/
Project-URL: Repository, https://github.com/LouisdeBruijn/waterfall-logging
